ordered_enum/__init__.py
ordered_enum/ordered_enum.py
ordered_enum/py.typed
ordered_enum-0.0.10.dist-info/licenses/LICENSE
ordered_enum-0.0.10.dist-info/WHEEL
ordered_enum-0.0.10.dist-info/METADATA
ordered_enum-0.0.10.dist-info/RECORD
