Metadata-Version: 2.4
Name: ordered_enum
Version: 0.0.10
Summary: A small library for adding total orderings to enums
Author-email: William Woodruff <william@yossarian.net>
Requires-Python: >=3.9
License-File: LICENSE
Requires-Dist: flake8 ; extra == "dev"
Requires-Dist: black ; extra == "dev"
Requires-Dist: isort[pyproject] ; extra == "dev"
Requires-Dist: pytest ; extra == "dev"
Requires-Dist: coverage ; extra == "dev"
Requires-Dist: build ; extra == "dev"
Requires-Dist: mypy ; extra == "dev"
Project-URL: Homepage, https://pypi.org/project/ordered_enum/
Project-URL: Issues, https://github.com/woodruffw/ordered_enum/issues
Project-URL: Source, https://github.com/woodruffw/ordered_enum
Provides-Extra: dev
